webeasyml
