Metadata-Version: 2.1
Name: webeasyml
Version: 0.1.6
Summary: wzai ; A simple ML web server,from wenzhou S&T High school
Author: linmy
Requires-Dist: flask<3.0.0,>=2.0.0
Requires-Dist: werkzeug<3.0.0,>=2.0.0
Requires-Dist: jinja2<4.0.0,>=3.0.0
